{
  "key": "bulldog-billionaires",
  "name": "Bulldog Billionaires",
  "symbol": "bone",
  "logoURI": "https://assets.coingecko.com/coins/images/24560/large/MIBYsiqF_400x400.jpg?1648195687",
  "website": "https://www.bulldogbillionaires.club/",
  "description": "BONE is the bulldog's lifeline and is the utility token for Solana NFT Project \"Bulldog Billionaires\". The token is essential for doghouses, auctions/raffles, bulldog upgrades, title claims/breeding, and much more. BONE token is deflationary meaning, BONE spent is BONE burned. BONE can only be retrieved by staking a Bulldog Billionaires NFT.",
  "coingeckoId": "bulldog-billionaires",
  "links": {
    "twitter": "https://twitter.com/bbsolana"
  }
}
