{
  "key": "binahero",
  "name": "BinaHero",
  "symbol": "hero",
  "logoURI": "https://assets.coingecko.com/coins/images/21890/large/binahero.jpg?1640248087",
  "website": "https://binahero.com/",
  "description": "BinaHero is a decentralized NFT game that integrates collection of NFT heroes, mining, market trading, and PVE. Players can play to earn in the game. We have already publicized game officially.",
  "coingeckoId": "binahero",
  "links": {
    "twitter": "https://twitter.com/binahero",
    "telegram": "https://t.me/BinaHero"
  },
  "networks": [
    {
      "chain": "binance-smart-chain",
      "network": "mainnet",
      "address": "0x78c3ade403438b37638304f9fbbfb1b76608c1bd",
      "decimals": 18
    }
  ]
}
